trytond/modules/health_contact_tracing/COPYING
trytond/modules/health_contact_tracing/README.rst
trytond/modules/health_contact_tracing/__init__.py
trytond/modules/health_contact_tracing/health_contact_tracing.py
trytond/modules/health_contact_tracing/health_contact_tracing_view.xml
trytond/modules/health_contact_tracing/icons/contact_tracing.svg
trytond/modules/health_contact_tracing/locale/ar.po
trytond/modules/health_contact_tracing/locale/de.po
trytond/modules/health_contact_tracing/locale/el.po
trytond/modules/health_contact_tracing/locale/eo.po
trytond/modules/health_contact_tracing/locale/es.po
trytond/modules/health_contact_tracing/locale/fr.po
trytond/modules/health_contact_tracing/locale/health_contact_tracing.pot
trytond/modules/health_contact_tracing/locale/it_IT.po
trytond/modules/health_contact_tracing/locale/ja_JP.po
trytond/modules/health_contact_tracing/locale/ka.po
trytond/modules/health_contact_tracing/locale/lo.po
trytond/modules/health_contact_tracing/locale/pt_BR.po
trytond/modules/health_contact_tracing/locale/sv.po
trytond/modules/health_contact_tracing/locale/tr.po
trytond/modules/health_contact_tracing/locale/uk.po
trytond/modules/health_contact_tracing/locale/zh_CN.po
trytond/modules/health_contact_tracing/pyproject.toml
trytond/modules/health_contact_tracing/tests/__init__.py
trytond/modules/health_contact_tracing/tests/test_health_contact_tracing.py
trytond/modules/health_contact_tracing/tryton.cfg
trytond/modules/health_contact_tracing/view/gnuhealth_contact_tracing_form.xml
trytond/modules/health_contact_tracing/view/gnuhealth_contact_tracing_tree.xml
gnuhealth_contact_tracing-5.0.2.dist-info/METADATA
gnuhealth_contact_tracing-5.0.2.dist-info/WHEEL
gnuhealth_contact_tracing-5.0.2.dist-info/licenses/COPYING
gnuhealth_contact_tracing-5.0.2.dist-info/RECORD
